pydndc/pydndc.pyi
pydndc/__init__.py
pydndc/pydndc.cpython-39-darwin.so
pydndc/py.typed
pydndc/__main__.py
pydndc-1.5.0.dist-info/RECORD
pydndc-1.5.0.dist-info/WHEEL
pydndc-1.5.0.dist-info/top_level.txt
pydndc-1.5.0.dist-info/METADATA
